customplotting/__init__.py
customplotting/general.py
customplotting/mscope.py
customplotting/version.py
customplotting-0.1.4.2.dist-info/LICENSE
customplotting-0.1.4.2.dist-info/METADATA
customplotting-0.1.4.2.dist-info/WHEEL
customplotting-0.1.4.2.dist-info/top_level.txt
customplotting-0.1.4.2.dist-info/RECORD
