Metadata-Version: 2.1
Name: customplotting
Version: 0.1.4.2
Summary: customplotting: make publishable quality science figures quickly
Home-page: https://github.com/SarthakJariwala/Custom-Plotting
Author: SARTHAK
Author-email: jariwala@uw.edu
Maintainer: Sarthak
Maintainer-email: jariwala@uw.edu
License: MIT
Platform: OS Independent
Classifier: Development Status :: 3 - Alpha
Classifier: Environment :: Console
Classifier: Intended Audience :: Science/Research
Classifier: License :: OSI Approved :: MIT License
Classifier: Operating System :: OS Independent
Classifier: Programming Language :: Python
Classifier: Topic :: Scientific/Engineering
Requires-Dist: numpy
Requires-Dist: matplotlib
Requires-Dist: matplotlib-scalebar
